{
  "昨日紐約收盤：": {
    "val": "USD 4570.00 / 盎司"
  },
  "-黃金 -": {
    "sell": "出 / 每台錢",
    "buy": "入 / 每台錢"
  },
  "1公斤裝王鼎進口條塊": {
    "sell": "17590",
    "buy": "17440"
  },
  "王鼎5台兩條塊": {
    "sell": "17595",
    "buy": "17445"
  },
  "王鼎壹台兩金龍條塊": {
    "sell": "17675",
    "buy": "17445"
  },
  "財富女神系列": {
    "sell": "價格請參考線上購物",
    "buy": "17465"
  },
  "-白金-": {
    "sell": "出 / 每台錢",
    "buy": "入 / 每台錢"
  },
  "PAMP 1盎司財富女神白金\"缺貨\"": {
    "sell": "8000",
    "buy": "7200"
  },
  "-白銀-": {
    "sell": "出 / 每台兩",
    "buy": "入 / 每台兩"
  },
  "999+ 王鼎白銀(1公斤規格)平裝 現貨": {
    "sell": "3185",
    "buy": "2705"
  },
  "999+ 王鼎白銀(1公斤規格)鏡面精裝 \"售完\"": {
    "sell": "3205",
    "buy": "2715"
  },
  "999+ 王鼎白銀(10盎司規格)盒裝 \"售完\"": {
    "sell": "3235",
    "buy": "2715"
  },
  "999+ 澳洲Perth Mint白銀(1公斤規格)  \"售完\"": {
    "sell": "3255",
    "buy": "2725"
  },
  "999+ ＰＡＭＰ白銀(1公斤規格) \"售完\"": {
    "sell": "3305",
    "buy": "2755"
  },
  "-黃金飾品收購-": {
    "val": "16920/ 每台錢"
  }
}