{
  "昨日紐約收盤：": {
    "val": "USD 4070.00 / 盎司"
  },
  "-黃金 -": {
    "sell": "出 / 每台錢",
    "buy": "入 / 每台錢"
  },
  "1公斤裝王鼎進口條塊": {
    "sell": "15900",
    "buy": "15700"
  },
  "王鼎5台兩條塊": {
    "sell": "15905",
    "buy": "15705"
  },
  "王鼎壹台兩金龍條塊": {
    "sell": "15985",
    "buy": "15705"
  },
  "財富女神系列": {
    "sell": "價格請參考線上購物",
    "buy": "15725"
  },
  "-白金-": {
    "sell": "出 / 每台錢",
    "buy": "入 / 每台錢"
  },
  "PAMP 1盎司財富女神白金\"缺貨\"": {
    "sell": "6950",
    "buy": "6150"
  },
  "-白銀-": {
    "sell": "出 / 每台兩",
    "buy": "入 / 每台兩"
  },
  "999+ 王鼎白銀(1公斤規格)平裝 \"現貨\"": {
    "sell": "2665",
    "buy": "2265"
  },
  "999+ 王鼎白銀(1公斤規格)鏡面精裝 \"現貨\"": {
    "sell": "2685",
    "buy": "2275"
  },
  "999+ 王鼎白銀(10盎司規格)盒裝 \"現貨\"": {
    "sell": "2715",
    "buy": "2275"
  },
  "999+ 澳洲Perth Mint白銀(1公斤規格) \"售完\"": {
    "sell": "2735",
    "buy": "2285"
  },
  "999+ ＰＡＭＰ白銀(1公斤規格)  \"現貨\"": {
    "sell": "2765",
    "buy": "2305"
  },
  "-黃金飾品收購-": {
    "val": "15300/ 每台錢"
  }
}